[{"date": "2024-12-02", "open": 4.91, "high": 4.97, "low": 4.88, "close": 4.97, "volume": 240295, "amount": 0, "pct_change": 0}, {"date": "2024-12-03", "open": 4.98, "high": 5.05, "low": 4.93, "close": 5.05, "volume": 314835, "amount": 0, "pct_change": 1.61}, {"date": "2024-12-04", "open": 5.02, "high": 5.03, "low": 4.94, "close": 4.95, "volume": 217314, "amount": 0, "pct_change": -1.98}, {"date": "2024-12-05", "open": 4.94, "high": 4.97, "low": 4.91, "close": 4.94, "volume": 168331, "amount": 0, "pct_change": -0.2}, {"date": "2024-12-06", "open": 4.94, "high": 5.08, "low": 4.94, "close": 5.07, "volume": 325973, "amount": 0, "pct_change": 2.63}, {"date": "2024-12-09", "open": 5.08, "high": 5.34, "low": 5.05, "close": 5.33, "volume": 864598, "amount": 0, "pct_change": 5.13}, {"date": "2024-12-10", "open": 5.39, "high": 5.45, "low": 5.15, "close": 5.18, "volume": 825571, "amount": 0, "pct_change": -2.81}, {"date": "2024-12-11", "open": 5.15, "high": 5.29, "low": 5.15, "close": 5.23, "volume": 418191, "amount": 0, "pct_change": 0.97}, {"date": "2024-12-12", "open": 5.25, "high": 5.37, "low": 5.23, "close": 5.3, "volume": 420515, "amount": 0, "pct_change": 1.34}, {"date": "2024-12-13", "open": 5.29, "high": 5.3, "low": 5.12, "close": 5.13, "volume": 330251, "amount": 0, "pct_change": -3.21}, {"date": "2024-12-16", "open": 5.14, "high": 5.24, "low": 5.14, "close": 5.21, "volume": 263183, "amount": 0, "pct_change": 1.56}, {"date": "2024-12-17", "open": 5.23, "high": 5.26, "low": 5.08, "close": 5.1, "volume": 250315, "amount": 0, "pct_change": -2.11}, {"date": "2024-12-18", "open": 5.16, "high": 5.47, "low": 5.14, "close": 5.44, "volume": 1016870, "amount": 0, "pct_change": 6.67}, {"date": "2024-12-19", "open": 5.27, "high": 5.49, "low": 5.24, "close": 5.34, "volume": 703973, "amount": 0, "pct_change": -1.84}, {"date": "2024-12-20", "open": 5.34, "high": 5.61, "low": 5.33, "close": 5.5, "volume": 905325, "amount": 0, "pct_change": 3.0}, {"date": "2024-12-23", "open": 5.47, "high": 5.57, "low": 5.36, "close": 5.4, "volume": 627710, "amount": 0, "pct_change": -1.82}, {"date": "2024-12-24", "open": 5.38, "high": 5.96, "low": 5.32, "close": 5.96, "volume": 1124872, "amount": 0, "pct_change": 10.37}, {"date": "2024-12-25", "open": 5.94, "high": 6.0, "low": 5.62, "close": 5.71, "volume": 1212859, "amount": 0, "pct_change": -4.19}, {"date": "2024-12-26", "open": 5.65, "high": 5.78, "low": 5.57, "close": 5.59, "volume": 846129, "amount": 0, "pct_change": -2.1}, {"date": "2024-12-27", "open": 5.58, "high": 6.04, "low": 5.52, "close": 5.9, "volume": 1172572, "amount": 0, "pct_change": 5.55}, {"date": "2024-12-30", "open": 5.78, "high": 5.9, "low": 5.66, "close": 5.68, "volume": 700842, "amount": 0, "pct_change": -3.73}, {"date": "2024-12-31", "open": 5.68, "high": 5.74, "low": 5.4, "close": 5.43, "volume": 588446, "amount": 0, "pct_change": -4.4}, {"date": "2025-01-02", "open": 5.35, "high": 5.41, "low": 5.02, "close": 5.1, "volume": 618054, "amount": 0, "pct_change": -6.08}, {"date": "2025-01-03", "open": 5.07, "high": 5.11, "low": 4.9, "close": 4.91, "volume": 401211, "amount": 0, "pct_change": -3.73}, {"date": "2025-01-06", "open": 4.88, "high": 5.05, "low": 4.84, "close": 4.95, "volume": 351792, "amount": 0, "pct_change": 0.81}, {"date": "2025-01-07", "open": 4.95, "high": 4.99, "low": 4.86, "close": 4.98, "volume": 277799, "amount": 0, "pct_change": 0.61}, {"date": "2025-01-08", "open": 4.96, "high": 4.96, "low": 4.72, "close": 4.86, "volume": 385992, "amount": 0, "pct_change": -2.41}, {"date": "2025-01-09", "open": 4.81, "high": 4.86, "low": 4.73, "close": 4.8, "volume": 218839, "amount": 0, "pct_change": -1.23}, {"date": "2025-01-10", "open": 4.79, "high": 4.83, "low": 4.6, "close": 4.62, "volume": 264599, "amount": 0, "pct_change": -3.75}, {"date": "2025-01-13", "open": 4.59, "high": 4.64, "low": 4.55, "close": 4.62, "volume": 194400, "amount": 0, "pct_change": 0.0}, {"date": "2025-01-14", "open": 4.6, "high": 4.79, "low": 4.6, "close": 4.77, "volume": 276981, "amount": 0, "pct_change": 3.25}, {"date": "2025-01-15", "open": 4.77, "high": 4.82, "low": 4.72, "close": 4.76, "volume": 208389, "amount": 0, "pct_change": -0.21}, {"date": "2025-01-16", "open": 4.78, "high": 5.0, "low": 4.78, "close": 4.84, "volume": 286510, "amount": 0, "pct_change": 1.68}, {"date": "2025-01-17", "open": 4.83, "high": 4.88, "low": 4.8, "close": 4.86, "volume": 193950, "amount": 0, "pct_change": 0.41}, {"date": "2025-01-20", "open": 4.88, "high": 4.93, "low": 4.85, "close": 4.87, "volume": 183774, "amount": 0, "pct_change": 0.21}, {"date": "2025-01-21", "open": 5.13, "high": 5.21, "low": 5.0, "close": 5.07, "volume": 658820, "amount": 0, "pct_change": 4.11}, {"date": "2025-01-22", "open": 5.01, "high": 5.14, "low": 4.97, "close": 5.07, "volume": 388500, "amount": 0, "pct_change": 0.0}, {"date": "2025-01-23", "open": 5.09, "high": 5.18, "low": 5.01, "close": 5.02, "volume": 304216, "amount": 0, "pct_change": -0.99}, {"date": "2025-01-24", "open": 4.99, "high": 5.05, "low": 4.96, "close": 5.01, "volume": 229386, "amount": 0, "pct_change": -0.2}, {"date": "2025-01-27", "open": 5.02, "high": 5.09, "low": 5.01, "close": 5.03, "volume": 241781, "amount": 0, "pct_change": 0.4}, {"date": "2025-02-05", "open": 5.07, "high": 5.07, "low": 4.94, "close": 4.98, "volume": 249934, "amount": 0, "pct_change": -0.99}, {"date": "2025-02-06", "open": 4.96, "high": 5.04, "low": 4.92, "close": 5.04, "volume": 262225, "amount": 0, "pct_change": 1.2}, {"date": "2025-02-07", "open": 5.02, "high": 5.3, "low": 4.99, "close": 5.17, "volume": 531191, "amount": 0, "pct_change": 2.58}, {"date": "2025-02-10", "open": 5.18, "high": 5.35, "low": 5.17, "close": 5.25, "volume": 424208, "amount": 0, "pct_change": 1.55}, {"date": "2025-02-11", "open": 5.24, "high": 5.27, "low": 5.15, "close": 5.23, "volume": 299405, "amount": 0, "pct_change": -0.38}, {"date": "2025-02-12", "open": 5.23, "high": 5.41, "low": 5.22, "close": 5.38, "volume": 377485, "amount": 0, "pct_change": 2.87}, {"date": "2025-02-13", "open": 5.37, "high": 5.45, "low": 5.33, "close": 5.36, "volume": 377658, "amount": 0, "pct_change": -0.37}, {"date": "2025-02-14", "open": 5.35, "high": 5.4, "low": 5.29, "close": 5.3, "volume": 241296, "amount": 0, "pct_change": -1.12}, {"date": "2025-02-17", "open": 5.29, "high": 5.37, "low": 5.22, "close": 5.37, "volume": 315305, "amount": 0, "pct_change": 1.32}, {"date": "2025-02-18", "open": 5.35, "high": 5.41, "low": 5.24, "close": 5.26, "volume": 241403, "amount": 0, "pct_change": -2.05}, {"date": "2025-02-19", "open": 5.26, "high": 5.26, "low": 5.14, "close": 5.22, "volume": 258990, "amount": 0, "pct_change": -0.76}, {"date": "2025-02-20", "open": 5.2, "high": 5.21, "low": 5.08, "close": 5.14, "volume": 247629, "amount": 0, "pct_change": -1.53}, {"date": "2025-02-21", "open": 5.16, "high": 5.19, "low": 5.11, "close": 5.14, "volume": 246209, "amount": 0, "pct_change": 0.0}, {"date": "2025-02-24", "open": 5.11, "high": 5.22, "low": 5.1, "close": 5.18, "volume": 200288, "amount": 0, "pct_change": 0.78}, {"date": "2025-02-25", "open": 5.15, "high": 5.19, "low": 5.08, "close": 5.11, "volume": 187664, "amount": 0, "pct_change": -1.35}, {"date": "2025-02-26", "open": 5.11, "high": 5.16, "low": 5.1, "close": 5.15, "volume": 190883, "amount": 0, "pct_change": 0.78}, {"date": "2025-02-27", "open": 5.16, "high": 5.33, "low": 5.15, "close": 5.23, "volume": 311440, "amount": 0, "pct_change": 1.55}, {"date": "2025-02-28", "open": 5.23, "high": 5.39, "low": 5.16, "close": 5.19, "volume": 402209, "amount": 0, "pct_change": -0.76}, {"date": "2025-03-03", "open": 5.18, "high": 5.29, "low": 5.16, "close": 5.19, "volume": 311892, "amount": 0, "pct_change": 0.0}, {"date": "2025-03-04", "open": 5.17, "high": 5.25, "low": 5.11, "close": 5.23, "volume": 188038, "amount": 0, "pct_change": 0.77}, {"date": "2025-03-05", "open": 5.22, "high": 5.22, "low": 5.09, "close": 5.12, "volume": 217703, "amount": 0, "pct_change": -2.1}, {"date": "2025-03-06", "open": 5.15, "high": 5.17, "low": 5.09, "close": 5.13, "volume": 213763, "amount": 0, "pct_change": 0.2}, {"date": "2025-03-07", "open": 5.1, "high": 5.14, "low": 5.06, "close": 5.1, "volume": 194278, "amount": 0, "pct_change": -0.58}, {"date": "2025-03-10", "open": 5.12, "high": 5.17, "low": 5.03, "close": 5.06, "volume": 231385, "amount": 0, "pct_change": -0.78}, {"date": "2025-03-11", "open": 5.03, "high": 5.08, "low": 4.99, "close": 5.05, "volume": 181279, "amount": 0, "pct_change": -0.2}, {"date": "2025-03-12", "open": 5.06, "high": 5.15, "low": 5.03, "close": 5.11, "volume": 293109, "amount": 0, "pct_change": 1.19}, {"date": "2025-03-13", "open": 5.13, "high": 5.27, "low": 5.11, "close": 5.27, "volume": 517642, "amount": 0, "pct_change": 3.13}, {"date": "2025-03-14", "open": 5.25, "high": 5.33, "low": 5.21, "close": 5.27, "volume": 351067, "amount": 0, "pct_change": 0.0}, {"date": "2025-03-17", "open": 5.25, "high": 5.33, "low": 5.24, "close": 5.28, "volume": 286601, "amount": 0, "pct_change": 0.19}, {"date": "2025-03-18", "open": 5.27, "high": 5.28, "low": 5.23, "close": 5.27, "volume": 185161, "amount": 0, "pct_change": -0.19}, {"date": "2025-03-19", "open": 5.27, "high": 5.49, "low": 5.24, "close": 5.44, "volume": 534615, "amount": 0, "pct_change": 3.23}, {"date": "2025-03-20", "open": 5.41, "high": 5.57, "low": 5.39, "close": 5.47, "volume": 384274, "amount": 0, "pct_change": 0.55}, {"date": "2025-03-21", "open": 5.47, "high": 5.69, "low": 5.43, "close": 5.57, "volume": 540123, "amount": 0, "pct_change": 1.83}, {"date": "2025-03-24", "open": 5.58, "high": 5.64, "low": 5.45, "close": 5.55, "volume": 457213, "amount": 0, "pct_change": -0.36}, {"date": "2025-03-25", "open": 5.55, "high": 5.84, "low": 5.49, "close": 5.73, "volume": 742259, "amount": 0, "pct_change": 3.24}, {"date": "2025-03-26", "open": 5.69, "high": 5.71, "low": 5.58, "close": 5.62, "volume": 441146, "amount": 0, "pct_change": -1.92}, {"date": "2025-03-27", "open": 5.6, "high": 5.64, "low": 5.44, "close": 5.46, "volume": 479954, "amount": 0, "pct_change": -2.85}, {"date": "2025-03-28", "open": 5.45, "high": 5.5, "low": 5.34, "close": 5.38, "volume": 347087, "amount": 0, "pct_change": -1.47}, {"date": "2025-03-31", "open": 5.37, "high": 5.59, "low": 5.33, "close": 5.49, "volume": 461649, "amount": 0, "pct_change": 2.04}, {"date": "2025-04-01", "open": 5.51, "high": 6.06, "low": 5.5, "close": 5.8, "volume": 937625, "amount": 0, "pct_change": 5.65}, {"date": "2025-04-02", "open": 5.71, "high": 5.82, "low": 5.62, "close": 5.76, "volume": 564001, "amount": 0, "pct_change": -0.69}, {"date": "2025-04-03", "open": 5.69, "high": 5.91, "low": 5.68, "close": 5.84, "volume": 657052, "amount": 0, "pct_change": 1.39}, {"date": "2025-04-07", "open": 5.52, "high": 5.75, "low": 5.23, "close": 5.51, "volume": 816868, "amount": 0, "pct_change": -5.65}, {"date": "2025-04-08", "open": 5.52, "high": 5.74, "low": 5.48, "close": 5.63, "volume": 752853, "amount": 0, "pct_change": 2.18}, {"date": "2025-04-09", "open": 5.54, "high": 5.61, "low": 5.17, "close": 5.48, "volume": 695573, "amount": 0, "pct_change": -2.66}, {"date": "2025-04-10", "open": 5.5, "high": 5.68, "low": 5.49, "close": 5.55, "volume": 592088, "amount": 0, "pct_change": 1.28}, {"date": "2025-04-11", "open": 5.45, "high": 5.58, "low": 5.43, "close": 5.44, "volume": 361417, "amount": 0, "pct_change": -1.98}, {"date": "2025-04-14", "open": 5.48, "high": 5.75, "low": 5.47, "close": 5.73, "volume": 635229, "amount": 0, "pct_change": 5.33}, {"date": "2025-04-15", "open": 6.0, "high": 6.33, "low": 5.95, "close": 6.33, "volume": 928096, "amount": 0, "pct_change": 10.47}, {"date": "2025-04-16", "open": 6.66, "high": 6.87, "low": 6.35, "close": 6.43, "volume": 2181043, "amount": 0, "pct_change": 1.58}, {"date": "2025-04-17", "open": 6.42, "high": 6.54, "low": 6.17, "close": 6.33, "volume": 1273688, "amount": 0, "pct_change": -1.56}, {"date": "2025-04-18", "open": 6.24, "high": 6.3, "low": 6.02, "close": 6.08, "volume": 976257, "amount": 0, "pct_change": -3.95}, {"date": "2025-04-21", "open": 6.04, "high": 6.26, "low": 6.04, "close": 6.2, "volume": 820065, "amount": 0, "pct_change": 1.97}, {"date": "2025-04-22", "open": 6.14, "high": 6.37, "low": 6.04, "close": 6.07, "volume": 843706, "amount": 0, "pct_change": -2.1}, {"date": "2025-04-23", "open": 6.08, "high": 6.25, "low": 6.0, "close": 6.25, "volume": 783475, "amount": 0, "pct_change": 2.97}, {"date": "2025-04-24", "open": 6.28, "high": 6.75, "low": 6.27, "close": 6.56, "volume": 1406197, "amount": 0, "pct_change": 4.96}, {"date": "2025-04-25", "open": 6.56, "high": 7.06, "low": 6.44, "close": 6.82, "volume": 1384219, "amount": 0, "pct_change": 3.96}, {"date": "2025-04-28", "open": 6.83, "high": 6.85, "low": 6.55, "close": 6.6, "volume": 925467, "amount": 0, "pct_change": -3.23}, {"date": "2025-04-29", "open": 6.52, "high": 6.53, "low": 6.21, "close": 6.3, "volume": 868913, "amount": 0, "pct_change": -4.55}, {"date": "2025-04-30", "open": 6.29, "high": 6.42, "low": 6.17, "close": 6.19, "volume": 564867, "amount": 0, "pct_change": -1.75}, {"date": "2025-05-06", "open": 6.23, "high": 6.34, "low": 6.17, "close": 6.34, "volume": 558011, "amount": 0, "pct_change": 2.42}, {"date": "2025-05-07", "open": 6.41, "high": 6.45, "low": 6.3, "close": 6.33, "volume": 645184, "amount": 0, "pct_change": -0.16}, {"date": "2025-05-08", "open": 6.33, "high": 6.56, "low": 6.3, "close": 6.49, "volume": 638601, "amount": 0, "pct_change": 2.53}, {"date": "2025-05-09", "open": 6.42, "high": 6.56, "low": 6.39, "close": 6.45, "volume": 580296, "amount": 0, "pct_change": -0.62}, {"date": "2025-05-12", "open": 6.44, "high": 6.47, "low": 6.28, "close": 6.33, "volume": 513129, "amount": 0, "pct_change": -1.86}, {"date": "2025-05-13", "open": 6.37, "high": 6.51, "low": 6.29, "close": 6.51, "volume": 555440, "amount": 0, "pct_change": 2.84}, {"date": "2025-05-14", "open": 6.46, "high": 6.5, "low": 6.37, "close": 6.47, "volume": 470147, "amount": 0, "pct_change": -0.61}, {"date": "2025-05-15", "open": 6.46, "high": 6.52, "low": 6.23, "close": 6.25, "volume": 518246, "amount": 0, "pct_change": -3.4}, {"date": "2025-05-16", "open": 6.22, "high": 6.45, "low": 6.21, "close": 6.28, "volume": 416035, "amount": 0, "pct_change": 0.48}, {"date": "2025-05-19", "open": 6.32, "high": 6.5, "low": 6.32, "close": 6.43, "volume": 438323, "amount": 0, "pct_change": 2.39}, {"date": "2025-05-20", "open": 6.41, "high": 6.59, "low": 6.38, "close": 6.58, "volume": 522778, "amount": 0, "pct_change": 2.33}, {"date": "2025-05-21", "open": 6.61, "high": 6.71, "low": 6.55, "close": 6.56, "volume": 592963, "amount": 0, "pct_change": -0.3}, {"date": "2025-05-22", "open": 6.51, "high": 6.61, "low": 6.35, "close": 6.39, "volume": 463147, "amount": 0, "pct_change": -2.59}, {"date": "2025-05-23", "open": 6.38, "high": 6.62, "low": 6.34, "close": 6.53, "volume": 633153, "amount": 0, "pct_change": 2.19}, {"date": "2025-05-26", "open": 6.67, "high": 7.0, "low": 6.55, "close": 6.89, "volume": 904242, "amount": 0, "pct_change": 5.51}, {"date": "2025-05-27", "open": 6.8, "high": 6.94, "low": 6.77, "close": 6.86, "volume": 430965, "amount": 0, "pct_change": -0.44}, {"date": "2025-05-28", "open": 6.84, "high": 6.99, "low": 6.74, "close": 6.77, "volume": 399309, "amount": 0, "pct_change": -1.31}, {"date": "2025-05-29", "open": 6.74, "high": 6.77, "low": 6.67, "close": 6.74, "volume": 280362, "amount": 0, "pct_change": -0.44}, {"date": "2025-05-30", "open": 6.74, "high": 6.83, "low": 6.55, "close": 6.56, "volume": 372488, "amount": 0, "pct_change": -2.67}, {"date": "2025-06-03", "open": 6.55, "high": 6.88, "low": 6.53, "close": 6.87, "volume": 441423, "amount": 0, "pct_change": 4.73}, {"date": "2025-06-04", "open": 6.86, "high": 6.95, "low": 6.8, "close": 6.92, "volume": 278421, "amount": 0, "pct_change": 0.73}, {"date": "2025-06-05", "open": 7.04, "high": 7.05, "low": 6.78, "close": 6.8, "volume": 314402, "amount": 0, "pct_change": -1.73}, {"date": "2025-06-06", "open": 6.78, "high": 6.86, "low": 6.72, "close": 6.85, "volume": 251625, "amount": 0, "pct_change": 0.74}, {"date": "2025-06-09", "open": 6.86, "high": 6.9, "low": 6.76, "close": 6.89, "volume": 266655, "amount": 0, "pct_change": 0.58}, {"date": "2025-06-10", "open": 6.87, "high": 7.08, "low": 6.85, "close": 6.98, "volume": 428193, "amount": 0, "pct_change": 1.31}, {"date": "2025-06-11", "open": 7.0, "high": 7.07, "low": 6.92, "close": 6.95, "volume": 268201, "amount": 0, "pct_change": -0.43}, {"date": "2025-06-12", "open": 6.98, "high": 6.99, "low": 6.88, "close": 6.92, "volume": 198788, "amount": 0, "pct_change": -0.43}, {"date": "2025-06-13", "open": 6.89, "high": 7.0, "low": 6.87, "close": 6.92, "volume": 234498, "amount": 0, "pct_change": 0.0}, {"date": "2025-06-16", "open": 6.92, "high": 7.21, "low": 6.89, "close": 7.1, "volume": 354840, "amount": 0, "pct_change": 2.6}, {"date": "2025-06-17", "open": 7.09, "high": 7.44, "low": 6.98, "close": 7.29, "volume": 409917, "amount": 0, "pct_change": 2.68}, {"date": "2025-06-18", "open": 7.29, "high": 7.37, "low": 7.14, "close": 7.35, "volume": 306505, "amount": 0, "pct_change": 0.82}, {"date": "2025-06-19", "open": 7.38, "high": 7.39, "low": 6.94, "close": 7.03, "volume": 495825, "amount": 0, "pct_change": -4.35}, {"date": "2025-06-20", "open": 7.0, "high": 7.1, "low": 6.95, "close": 7.02, "volume": 201052, "amount": 0, "pct_change": -0.14}, {"date": "2025-06-23", "open": 6.96, "high": 7.06, "low": 6.85, "close": 7.03, "volume": 297054, "amount": 0, "pct_change": 0.14}, {"date": "2025-06-24", "open": 7.0, "high": 7.35, "low": 7.0, "close": 7.23, "volume": 304685, "amount": 0, "pct_change": 2.84}, {"date": "2025-06-25", "open": 7.24, "high": 7.29, "low": 7.13, "close": 7.2, "volume": 252116, "amount": 0, "pct_change": -0.41}, {"date": "2025-06-26", "open": 7.17, "high": 7.29, "low": 7.07, "close": 7.13, "volume": 290337, "amount": 0, "pct_change": -0.97}, {"date": "2025-06-27", "open": 7.13, "high": 7.2, "low": 6.83, "close": 6.89, "volume": 456906, "amount": 0, "pct_change": -3.37}, {"date": "2025-06-30", "open": 6.81, "high": 6.89, "low": 6.7, "close": 6.81, "volume": 423356, "amount": 0, "pct_change": -1.16}, {"date": "2025-07-01", "open": 6.81, "high": 7.06, "low": 6.77, "close": 6.95, "volume": 360140, "amount": 0, "pct_change": 2.06}, {"date": "2025-07-02", "open": 6.99, "high": 7.15, "low": 6.95, "close": 7.07, "volume": 369998, "amount": 0, "pct_change": 1.73}, {"date": "2025-07-03", "open": 7.07, "high": 7.1, "low": 6.99, "close": 7.06, "volume": 193431, "amount": 0, "pct_change": -0.14}, {"date": "2025-07-04", "open": 7.1, "high": 7.24, "low": 7.08, "close": 7.18, "volume": 319031, "amount": 0, "pct_change": 1.7}, {"date": "2025-07-07", "open": 7.48, "high": 7.75, "low": 7.21, "close": 7.66, "volume": 714433, "amount": 0, "pct_change": 6.69}, {"date": "2025-07-08", "open": 7.7, "high": 7.71, "low": 7.44, "close": 7.53, "volume": 502083, "amount": 0, "pct_change": -1.7}, {"date": "2025-07-09", "open": 7.48, "high": 7.66, "low": 7.46, "close": 7.48, "volume": 300942, "amount": 0, "pct_change": -0.66}, {"date": "2025-07-10", "open": 7.48, "high": 7.6, "low": 7.38, "close": 7.49, "volume": 276055, "amount": 0, "pct_change": 0.13}, {"date": "2025-07-11", "open": 7.45, "high": 7.56, "low": 7.35, "close": 7.52, "volume": 266522, "amount": 0, "pct_change": 0.4}, {"date": "2025-07-14", "open": 7.79, "high": 8.28, "low": 7.73, "close": 8.28, "volume": 440742, "amount": 0, "pct_change": 10.11}, {"date": "2025-07-15", "open": 8.32, "high": 8.39, "low": 7.75, "close": 7.89, "volume": 1279815, "amount": 0, "pct_change": -4.71}, {"date": "2025-07-16", "open": 7.98, "high": 8.04, "low": 7.63, "close": 7.68, "volume": 642299, "amount": 0, "pct_change": -2.66}, {"date": "2025-07-17", "open": 7.7, "high": 7.75, "low": 7.62, "close": 7.68, "volume": 378035, "amount": 0, "pct_change": 0.0}, {"date": "2025-07-18", "open": 7.69, "high": 7.73, "low": 7.58, "close": 7.66, "volume": 392618, "amount": 0, "pct_change": -0.26}, {"date": "2025-07-21", "open": 7.61, "high": 7.71, "low": 7.61, "close": 7.67, "volume": 343126, "amount": 0, "pct_change": 0.13}, {"date": "2025-07-22", "open": 7.65, "high": 7.67, "low": 7.46, "close": 7.55, "volume": 505053, "amount": 0, "pct_change": -1.56}, {"date": "2025-07-23", "open": 7.53, "high": 7.61, "low": 7.38, "close": 7.4, "volume": 439467, "amount": 0, "pct_change": -1.99}, {"date": "2025-07-24", "open": 7.38, "high": 7.42, "low": 7.3, "close": 7.39, "volume": 376111, "amount": 0, "pct_change": -0.14}, {"date": "2025-07-25", "open": 7.4, "high": 7.43, "low": 7.28, "close": 7.29, "volume": 331788, "amount": 0, "pct_change": -1.35}, {"date": "2025-07-28", "open": 7.33, "high": 7.34, "low": 7.2, "close": 7.24, "volume": 348524, "amount": 0, "pct_change": -0.69}, {"date": "2025-07-29", "open": 7.25, "high": 7.26, "low": 7.12, "close": 7.18, "volume": 283911, "amount": 0, "pct_change": -0.83}, {"date": "2025-07-30", "open": 7.18, "high": 7.27, "low": 7.15, "close": 7.19, "volume": 287946, "amount": 0, "pct_change": 0.14}, {"date": "2025-07-31", "open": 7.21, "high": 7.22, "low": 7.04, "close": 7.06, "volume": 263417, "amount": 0, "pct_change": -1.81}, {"date": "2025-08-01", "open": 7.04, "high": 7.14, "low": 7.03, "close": 7.12, "volume": 188262, "amount": 0, "pct_change": 0.85}, {"date": "2025-08-04", "open": 7.14, "high": 7.25, "low": 7.11, "close": 7.24, "volume": 232713, "amount": 0, "pct_change": 1.69}, {"date": "2025-08-05", "open": 7.22, "high": 7.26, "low": 7.18, "close": 7.26, "volume": 171466, "amount": 0, "pct_change": 0.28}, {"date": "2025-08-06", "open": 7.24, "high": 7.28, "low": 7.2, "close": 7.23, "volume": 144242, "amount": 0, "pct_change": -0.41}, {"date": "2025-08-07", "open": 7.25, "high": 7.25, "low": 7.15, "close": 7.18, "volume": 161488, "amount": 0, "pct_change": -0.69}, {"date": "2025-08-08", "open": 7.16, "high": 7.3, "low": 7.16, "close": 7.27, "volume": 215371, "amount": 0, "pct_change": 1.25}, {"date": "2025-08-11", "open": 7.3, "high": 7.32, "low": 7.21, "close": 7.28, "volume": 227602, "amount": 0, "pct_change": 0.14}, {"date": "2025-08-12", "open": 7.3, "high": 7.37, "low": 7.28, "close": 7.36, "volume": 218315, "amount": 0, "pct_change": 1.1}, {"date": "2025-08-13", "open": 7.37, "high": 7.45, "low": 7.35, "close": 7.44, "volume": 249356, "amount": 0, "pct_change": 1.09}, {"date": "2025-08-14", "open": 7.44, "high": 7.45, "low": 7.27, "close": 7.29, "volume": 249477, "amount": 0, "pct_change": -2.02}, {"date": "2025-08-15", "open": 7.28, "high": 7.36, "low": 7.26, "close": 7.34, "volume": 254361, "amount": 0, "pct_change": 0.69}, {"date": "2025-08-18", "open": 7.27, "high": 7.41, "low": 7.17, "close": 7.3, "volume": 511917, "amount": 0, "pct_change": -0.54}, {"date": "2025-08-19", "open": 7.33, "high": 7.45, "low": 7.3, "close": 7.4, "volume": 448795, "amount": 0, "pct_change": 1.37}, {"date": "2025-08-20", "open": 7.38, "high": 7.43, "low": 7.35, "close": 7.43, "volume": 287097, "amount": 0, "pct_change": 0.41}, {"date": "2025-08-21", "open": 7.45, "high": 7.49, "low": 7.42, "close": 7.46, "volume": 308491, "amount": 0, "pct_change": 0.4}, {"date": "2025-08-22", "open": 7.48, "high": 7.49, "low": 7.33, "close": 7.42, "volume": 255690, "amount": 0, "pct_change": -0.54}, {"date": "2025-08-25", "open": 7.45, "high": 7.48, "low": 7.39, "close": 7.42, "volume": 323437, "amount": 0, "pct_change": 0.0}, {"date": "2025-08-26", "open": 7.42, "high": 7.44, "low": 7.35, "close": 7.37, "volume": 250645, "amount": 0, "pct_change": -0.67}, {"date": "2025-08-27", "open": 7.36, "high": 7.46, "low": 7.17, "close": 7.17, "volume": 392067, "amount": 0, "pct_change": -2.71}, {"date": "2025-08-28", "open": 7.17, "high": 7.24, "low": 6.95, "close": 7.13, "volume": 362071, "amount": 0, "pct_change": -0.56}, {"date": "2025-08-29", "open": 7.14, "high": 7.25, "low": 7.09, "close": 7.14, "volume": 218802, "amount": 0, "pct_change": 0.14}, {"date": "2025-09-01", "open": 7.15, "high": 7.49, "low": 7.13, "close": 7.48, "volume": 614047, "amount": 0, "pct_change": 4.76}, {"date": "2025-09-02", "open": 7.46, "high": 7.5, "low": 7.35, "close": 7.43, "volume": 357748, "amount": 0, "pct_change": -0.67}, {"date": "2025-09-03", "open": 7.43, "high": 7.47, "low": 7.24, "close": 7.32, "volume": 229268, "amount": 0, "pct_change": -1.48}, {"date": "2025-09-04", "open": 7.31, "high": 7.43, "low": 7.29, "close": 7.36, "volume": 275963, "amount": 0, "pct_change": 0.55}, {"date": "2025-09-05", "open": 7.37, "high": 7.5, "low": 7.34, "close": 7.48, "volume": 291313, "amount": 0, "pct_change": 1.63}, {"date": "2025-09-08", "open": 7.49, "high": 7.83, "low": 7.47, "close": 7.76, "volume": 478059, "amount": 0, "pct_change": 3.74}, {"date": "2025-09-09", "open": 7.73, "high": 7.79, "low": 7.57, "close": 7.6, "volume": 306658, "amount": 0, "pct_change": -2.06}, {"date": "2025-09-10", "open": 7.59, "high": 7.66, "low": 7.51, "close": 7.6, "volume": 216471, "amount": 0, "pct_change": 0.0}, {"date": "2025-09-11", "open": 7.56, "high": 7.63, "low": 7.48, "close": 7.62, "volume": 215665, "amount": 0, "pct_change": 0.26}, {"date": "2025-09-12", "open": 7.63, "high": 7.74, "low": 7.57, "close": 7.66, "volume": 213970, "amount": 0, "pct_change": 0.52}, {"date": "2025-09-15", "open": 7.63, "high": 7.66, "low": 7.46, "close": 7.48, "volume": 210859, "amount": 0, "pct_change": -2.35}, {"date": "2025-09-16", "open": 7.5, "high": 7.5, "low": 7.26, "close": 7.35, "volume": 211270, "amount": 0, "pct_change": -1.74}, {"date": "2025-09-17", "open": 7.35, "high": 7.38, "low": 7.23, "close": 7.29, "volume": 186852, "amount": 0, "pct_change": -0.82}, {"date": "2025-09-18", "open": 7.3, "high": 7.3, "low": 7.03, "close": 7.05, "volume": 311818, "amount": 0, "pct_change": -3.29}, {"date": "2025-09-19", "open": 7.06, "high": 7.12, "low": 7.04, "close": 7.08, "volume": 150432, "amount": 0, "pct_change": 0.43}, {"date": "2025-09-22", "open": 7.1, "high": 7.11, "low": 6.91, "close": 7.0, "volume": 186055, "amount": 0, "pct_change": -1.13}, {"date": "2025-09-23", "open": 6.97, "high": 7.02, "low": 6.87, "close": 7.0, "volume": 147848, "amount": 0, "pct_change": 0.0}, {"date": "2025-09-24", "open": 6.99, "high": 7.04, "low": 6.91, "close": 7.03, "volume": 172006, "amount": 0, "pct_change": 0.43}, {"date": "2025-09-25", "open": 7.01, "high": 7.03, "low": 6.91, "close": 6.93, "volume": 180820, "amount": 0, "pct_change": -1.42}, {"date": "2025-09-26", "open": 6.91, "high": 7.16, "low": 6.87, "close": 7.1, "volume": 238910, "amount": 0, "pct_change": 2.45}, {"date": "2025-09-29", "open": 7.1, "high": 7.27, "low": 7.02, "close": 7.2, "volume": 272485, "amount": 0, "pct_change": 1.41}, {"date": "2025-09-30", "open": 7.17, "high": 7.3, "low": 7.15, "close": 7.29, "volume": 193260, "amount": 0, "pct_change": 1.25}, {"date": "2025-10-09", "open": 7.28, "high": 7.78, "low": 7.27, "close": 7.74, "volume": 568655, "amount": 0, "pct_change": 6.17}, {"date": "2025-10-10", "open": 7.71, "high": 8.06, "low": 7.63, "close": 7.98, "volume": 507098, "amount": 0, "pct_change": 3.1}, {"date": "2025-10-13", "open": 7.77, "high": 8.21, "low": 7.76, "close": 8.15, "volume": 563578, "amount": 0, "pct_change": 2.13}, {"date": "2025-10-14", "open": 8.16, "high": 8.42, "low": 8.12, "close": 8.3, "volume": 663790, "amount": 0, "pct_change": 1.84}, {"date": "2025-10-15", "open": 8.56, "high": 9.06, "low": 8.23, "close": 8.73, "volume": 1238730, "amount": 0, "pct_change": 5.18}, {"date": "2025-10-16", "open": 8.59, "high": 8.99, "low": 8.5, "close": 8.86, "volume": 863637, "amount": 0, "pct_change": 1.49}, {"date": "2025-10-17", "open": 8.9, "high": 9.35, "low": 8.78, "close": 9.33, "volume": 984890, "amount": 0, "pct_change": 5.3}, {"date": "2025-10-20", "open": 9.52, "high": 9.76, "low": 8.97, "close": 9.19, "volume": 1186207, "amount": 0, "pct_change": -1.5}, {"date": "2025-10-21", "open": 9.2, "high": 9.56, "low": 8.91, "close": 9.48, "volume": 909164, "amount": 0, "pct_change": 3.16}, {"date": "2025-10-22", "open": 9.3, "high": 9.72, "low": 9.23, "close": 9.43, "volume": 661293, "amount": 0, "pct_change": -0.53}, {"date": "2025-10-23", "open": 9.34, "high": 9.85, "low": 9.32, "close": 9.65, "volume": 625925, "amount": 0, "pct_change": 2.33}, {"date": "2025-10-24", "open": 9.59, "high": 9.64, "low": 9.34, "close": 9.45, "volume": 553600, "amount": 0, "pct_change": -2.07}, {"date": "2025-10-27", "open": 9.4, "high": 9.72, "low": 9.35, "close": 9.61, "volume": 478785, "amount": 0, "pct_change": 1.69}, {"date": "2025-10-28", "open": 9.6, "high": 9.72, "low": 9.48, "close": 9.49, "volume": 358371, "amount": 0, "pct_change": -1.25}, {"date": "2025-10-29", "open": 9.49, "high": 9.58, "low": 9.29, "close": 9.54, "volume": 357450, "amount": 0, "pct_change": 0.53}, {"date": "2025-10-30", "open": 9.55, "high": 9.64, "low": 9.42, "close": 9.5, "volume": 309937, "amount": 0, "pct_change": -0.42}, {"date": "2025-10-31", "open": 9.6, "high": 9.6, "low": 8.95, "close": 9.02, "volume": 638138, "amount": 0, "pct_change": -5.05}, {"date": "2025-11-03", "open": 9.09, "high": 9.13, "low": 8.67, "close": 8.86, "volume": 497772, "amount": 0, "pct_change": -1.77}, {"date": "2025-11-04", "open": 8.85, "high": 8.93, "low": 8.61, "close": 8.67, "volume": 380996, "amount": 0, "pct_change": -2.14}, {"date": "2025-11-05", "open": 8.67, "high": 8.83, "low": 8.6, "close": 8.75, "volume": 287626, "amount": 0, "pct_change": 0.92}, {"date": "2025-11-06", "open": 8.81, "high": 8.96, "low": 8.72, "close": 8.76, "volume": 296925, "amount": 0, "pct_change": 0.11}, {"date": "2025-11-07", "open": 8.73, "high": 8.97, "low": 8.7, "close": 8.78, "volume": 284662, "amount": 0, "pct_change": 0.23}, {"date": "2025-11-10", "open": 8.83, "high": 8.96, "low": 8.82, "close": 8.84, "volume": 261844, "amount": 0, "pct_change": 0.68}, {"date": "2025-11-11", "open": 8.85, "high": 8.88, "low": 8.74, "close": 8.79, "volume": 238341, "amount": 0, "pct_change": -0.57}, {"date": "2025-11-12", "open": 8.76, "high": 8.79, "low": 8.6, "close": 8.62, "volume": 239497, "amount": 0, "pct_change": -1.93}, {"date": "2025-11-13", "open": 8.63, "high": 8.65, "low": 8.51, "close": 8.63, "volume": 192716, "amount": 0, "pct_change": 0.12}, {"date": "2025-11-14", "open": 8.59, "high": 8.65, "low": 8.48, "close": 8.49, "volume": 179770, "amount": 0, "pct_change": -1.62}, {"date": "2025-11-17", "open": 8.46, "high": 8.49, "low": 8.31, "close": 8.37, "volume": 190327, "amount": 0, "pct_change": -1.41}, {"date": "2025-11-18", "open": 8.34, "high": 8.39, "low": 8.12, "close": 8.19, "volume": 176234, "amount": 0, "pct_change": -2.15}, {"date": "2025-11-19", "open": 8.18, "high": 8.25, "low": 8.11, "close": 8.16, "volume": 161445, "amount": 0, "pct_change": -0.37}, {"date": "2025-11-20", "open": 8.2, "high": 8.29, "low": 8.12, "close": 8.14, "volume": 138169, "amount": 0, "pct_change": -0.25}, {"date": "2025-11-21", "open": 8.15, "high": 8.18, "low": 7.87, "close": 7.87, "volume": 255676, "amount": 0, "pct_change": -3.32}, {"date": "2025-11-24", "open": 7.97, "high": 8.07, "low": 7.85, "close": 7.86, "volume": 226071, "amount": 0, "pct_change": -0.13}, {"date": "2025-11-25", "open": 7.95, "high": 8.09, "low": 7.91, "close": 7.94, "volume": 200944, "amount": 0, "pct_change": 1.02}, {"date": "2025-11-26", "open": 7.96, "high": 8.04, "low": 7.93, "close": 7.98, "volume": 173814, "amount": 0, "pct_change": 0.5}, {"date": "2025-11-27", "open": 7.96, "high": 8.13, "low": 7.95, "close": 8.02, "volume": 188444, "amount": 0, "pct_change": 0.5}, {"date": "2025-11-28", "open": 8.06, "high": 8.08, "low": 7.95, "close": 8.03, "volume": 166111, "amount": 0, "pct_change": 0.12}, {"date": "2025-12-01", "open": 8.03, "high": 8.09, "low": 7.98, "close": 8.06, "volume": 236959, "amount": 0, "pct_change": 0.37}, {"date": "2025-12-02", "open": 8.02, "high": 8.05, "low": 7.97, "close": 8.0, "volume": 144562, "amount": 0, "pct_change": -0.74}, {"date": "2025-12-03", "open": 8.0, "high": 8.25, "low": 8.0, "close": 8.2, "volume": 342352, "amount": 0, "pct_change": 2.5}, {"date": "2025-12-04", "open": 8.25, "high": 8.25, "low": 8.03, "close": 8.08, "volume": 304742, "amount": 0, "pct_change": -1.46}, {"date": "2025-12-05", "open": 8.07, "high": 8.09, "low": 7.99, "close": 8.04, "volume": 195309, "amount": 0, "pct_change": -0.5}, {"date": "2025-12-08", "open": 8.04, "high": 8.06, "low": 7.91, "close": 7.97, "volume": 224813, "amount": 0, "pct_change": -0.87}, {"date": "2025-12-09", "open": 7.97, "high": 8.08, "low": 7.94, "close": 8.01, "volume": 161434, "amount": 0, "pct_change": 0.5}, {"date": "2025-12-10", "open": 7.99, "high": 8.05, "low": 7.97, "close": 8.01, "volume": 130258, "amount": 0, "pct_change": 0.0}, {"date": "2025-12-11", "open": 8.01, "high": 8.16, "low": 8.0, "close": 8.06, "volume": 232675, "amount": 0, "pct_change": 0.62}, {"date": "2025-12-12", "open": 8.03, "high": 8.24, "low": 8.03, "close": 8.19, "volume": 214168, "amount": 0, "pct_change": 1.61}, {"date": "2025-12-15", "open": 8.16, "high": 8.47, "low": 8.11, "close": 8.36, "volume": 398361, "amount": 0, "pct_change": 2.08}, {"date": "2025-12-16", "open": 8.34, "high": 8.34, "low": 7.99, "close": 8.05, "volume": 391811, "amount": 0, "pct_change": -3.71}, {"date": "2025-12-17", "open": 8.04, "high": 8.15, "low": 7.94, "close": 8.12, "volume": 201711, "amount": 0, "pct_change": 0.87}, {"date": "2025-12-18", "open": 8.07, "high": 8.15, "low": 8.03, "close": 8.09, "volume": 153203, "amount": 0, "pct_change": -0.37}, {"date": "2025-12-19", "open": 8.09, "high": 8.25, "low": 8.07, "close": 8.16, "volume": 164257, "amount": 0, "pct_change": 0.87}, {"date": "2025-12-22", "open": 8.15, "high": 8.29, "low": 8.14, "close": 8.22, "volume": 170767, "amount": 0, "pct_change": 0.74}, {"date": "2025-12-23", "open": 8.26, "high": 8.58, "low": 8.23, "close": 8.46, "volume": 423622, "amount": 0, "pct_change": 2.92}, {"date": "2025-12-24", "open": 8.36, "high": 8.48, "low": 8.28, "close": 8.47, "volume": 239121, "amount": 0, "pct_change": 0.12}, {"date": "2025-12-25", "open": 8.49, "high": 8.79, "low": 8.49, "close": 8.68, "volume": 363577, "amount": 0, "pct_change": 2.48}, {"date": "2025-12-26", "open": 8.66, "high": 8.75, "low": 8.6, "close": 8.71, "volume": 232318, "amount": 0, "pct_change": 0.35}, {"date": "2025-12-29", "open": 8.75, "high": 8.76, "low": 8.35, "close": 8.38, "volume": 361623, "amount": 0, "pct_change": -3.79}, {"date": "2025-12-30", "open": 8.36, "high": 8.44, "low": 8.26, "close": 8.33, "volume": 217628, "amount": 0, "pct_change": -0.6}, {"date": "2025-12-31", "open": 8.33, "high": 8.46, "low": 8.32, "close": 8.43, "volume": 172648, "amount": 0, "pct_change": 1.2}, {"date": "2026-01-05", "open": 8.51, "high": 8.56, "low": 8.39, "close": 8.51, "volume": 246226, "amount": 0, "pct_change": 0.95}, {"date": "2026-01-06", "open": 8.5, "high": 8.63, "low": 8.47, "close": 8.62, "volume": 234643, "amount": 0, "pct_change": 1.29}, {"date": "2026-01-07", "open": 8.63, "high": 8.76, "low": 8.58, "close": 8.63, "volume": 228845, "amount": 0, "pct_change": 0.12}, {"date": "2026-01-08", "open": 8.6, "high": 8.69, "low": 8.54, "close": 8.57, "volume": 222685, "amount": 0, "pct_change": -0.7}, {"date": "2026-01-09", "open": 8.57, "high": 8.72, "low": 8.55, "close": 8.72, "volume": 245843, "amount": 0, "pct_change": 1.75}, {"date": "2026-01-12", "open": 8.73, "high": 8.8, "low": 8.59, "close": 8.7, "volume": 267111, "amount": 0, "pct_change": -0.23}, {"date": "2026-01-13", "open": 8.69, "high": 8.86, "low": 8.64, "close": 8.74, "volume": 289062, "amount": 0, "pct_change": 0.46}, {"date": "2026-01-14", "open": 8.73, "high": 8.83, "low": 8.63, "close": 8.72, "volume": 279745, "amount": 0, "pct_change": -0.23}, {"date": "2026-01-15", "open": 8.69, "high": 8.93, "low": 8.63, "close": 8.92, "volume": 321274, "amount": 0, "pct_change": 2.29}, {"date": "2026-01-16", "open": 8.97, "high": 9.09, "low": 8.8, "close": 8.81, "volume": 315776, "amount": 0, "pct_change": -1.23}, {"date": "2026-01-19", "open": 8.8, "high": 9.11, "low": 8.79, "close": 9.08, "volume": 280780, "amount": 0, "pct_change": 3.06}, {"date": "2026-01-20", "open": 9.13, "high": 9.27, "low": 9.04, "close": 9.27, "volume": 271195, "amount": 0, "pct_change": 2.09}, {"date": "2026-01-21", "open": 9.18, "high": 9.18, "low": 8.86, "close": 8.92, "volume": 608078, "amount": 0, "pct_change": -3.78}, {"date": "2026-01-22", "open": 8.98, "high": 9.0, "low": 8.75, "close": 8.82, "volume": 374409, "amount": 0, "pct_change": -1.12}, {"date": "2026-01-23", "open": 8.85, "high": 8.87, "low": 8.77, "close": 8.84, "volume": 264944, "amount": 0, "pct_change": 0.23}, {"date": "2026-01-26", "open": 8.83, "high": 8.84, "low": 8.59, "close": 8.65, "volume": 389932, "amount": 0, "pct_change": -2.15}, {"date": "2026-01-27", "open": 8.66, "high": 8.66, "low": 8.4, "close": 8.49, "volume": 302936, "amount": 0, "pct_change": -1.85}, {"date": "2026-01-28", "open": 8.49, "high": 8.8, "low": 8.44, "close": 8.78, "volume": 355496, "amount": 0, "pct_change": 3.42}, {"date": "2026-01-29", "open": 8.76, "high": 8.77, "low": 8.58, "close": 8.65, "volume": 220051, "amount": 0, "pct_change": -1.48}, {"date": "2026-01-30", "open": 8.64, "high": 8.79, "low": 8.54, "close": 8.73, "volume": 232519, "amount": 0, "pct_change": 0.92}, {"date": "2026-02-02", "open": 8.75, "high": 8.78, "low": 8.45, "close": 8.46, "volume": 274238, "amount": 0, "pct_change": -3.09}, {"date": "2026-02-03", "open": 8.54, "high": 8.61, "low": 8.41, "close": 8.46, "volume": 228737, "amount": 0, "pct_change": 0.0}, {"date": "2026-02-04", "open": 8.45, "high": 8.55, "low": 8.4, "close": 8.54, "volume": 198780, "amount": 0, "pct_change": 0.95}, {"date": "2026-02-05", "open": 8.51, "high": 8.52, "low": 8.28, "close": 8.35, "volume": 233888, "amount": 0, "pct_change": -2.22}, {"date": "2026-02-06", "open": 8.31, "high": 8.62, "low": 8.27, "close": 8.53, "volume": 256461, "amount": 0, "pct_change": 2.16}, {"date": "2026-02-09", "open": 8.56, "high": 8.61, "low": 8.48, "close": 8.53, "volume": 164784, "amount": 0, "pct_change": 0.0}, {"date": "2026-02-10", "open": 8.51, "high": 8.54, "low": 8.4, "close": 8.41, "volume": 129020, "amount": 0, "pct_change": -1.41}, {"date": "2026-02-11", "open": 8.4, "high": 8.56, "low": 8.4, "close": 8.47, "volume": 135151, "amount": 0, "pct_change": 0.71}, {"date": "2026-02-12", "open": 8.51, "high": 8.9, "low": 8.5, "close": 8.86, "volume": 421828, "amount": 0, "pct_change": 4.6}, {"date": "2026-02-13", "open": 8.8, "high": 8.84, "low": 8.35, "close": 8.36, "volume": 478290, "amount": 0, "pct_change": -5.64}, {"date": "2026-02-24", "open": 8.47, "high": 8.7, "low": 8.4, "close": 8.65, "volume": 402075, "amount": 0, "pct_change": 3.47}, {"date": "2026-02-25", "open": 8.67, "high": 8.95, "low": 8.66, "close": 8.84, "volume": 417532, "amount": 0, "pct_change": 2.2}, {"date": "2026-02-26", "open": 8.86, "high": 9.14, "low": 8.83, "close": 9.03, "volume": 367376, "amount": 0, "pct_change": 2.15}, {"date": "2026-02-27", "open": 8.97, "high": 9.6, "low": 8.92, "close": 9.5, "volume": 568687, "amount": 0, "pct_change": 5.2}, {"date": "2026-03-02", "open": 9.31, "high": 9.65, "low": 9.31, "close": 9.5, "volume": 545871, "amount": 0, "pct_change": 0.0}, {"date": "2026-03-03", "open": 9.51, "high": 9.61, "low": 9.2, "close": 9.25, "volume": 541221, "amount": 0, "pct_change": -2.63}, {"date": "2026-03-04", "open": 9.08, "high": 9.44, "low": 9.07, "close": 9.24, "volume": 338647, "amount": 0, "pct_change": -0.11}, {"date": "2026-03-05", "open": 9.36, "high": 9.63, "low": 9.34, "close": 9.47, "volume": 417946, "amount": 0, "pct_change": 2.49}, {"date": "2026-03-06", "open": 9.4, "high": 9.72, "low": 9.38, "close": 9.58, "volume": 373098, "amount": 0, "pct_change": 1.16}, {"date": "2026-03-09", "open": 9.59, "high": 9.74, "low": 9.5, "close": 9.58, "volume": 419823, "amount": 0, "pct_change": 0.0}, {"date": "2026-03-10", "open": 9.5, "high": 9.7, "low": 9.42, "close": 9.51, "volume": 349676, "amount": 0, "pct_change": -0.73}, {"date": "2026-03-11", "open": 9.52, "high": 9.74, "low": 9.3, "close": 9.73, "volume": 455009, "amount": 0, "pct_change": 2.31}, {"date": "2026-03-12", "open": 9.73, "high": 10.7, "low": 9.7, "close": 10.7, "volume": 1034859, "amount": 0, "pct_change": 9.97}, {"date": "2026-03-13", "open": 10.99, "high": 10.99, "low": 10.15, "close": 10.19, "volume": 1289472, "amount": 0, "pct_change": -4.77}, {"date": "2026-03-16", "open": 10.19, "high": 10.25, "low": 9.48, "close": 9.52, "volume": 756278, "amount": 0, "pct_change": -6.58}, {"date": "2026-03-17", "open": 9.55, "high": 9.72, "low": 9.34, "close": 9.42, "volume": 562779, "amount": 0, "pct_change": -1.05}, {"date": "2026-03-18", "open": 9.56, "high": 10.12, "low": 9.54, "close": 9.88, "volume": 741256, "amount": 0, "pct_change": 4.88}, {"date": "2026-03-19", "open": 9.88, "high": 9.94, "low": 9.55, "close": 9.58, "volume": 502920, "amount": 0, "pct_change": -3.04}, {"date": "2026-03-20", "open": 9.61, "high": 9.97, "low": 9.49, "close": 9.69, "volume": 596297, "amount": 0, "pct_change": 1.15}, {"date": "2026-03-23", "open": 9.32, "high": 9.64, "low": 9.06, "close": 9.18, "volume": 590109, "amount": 0, "pct_change": -5.26}, {"date": "2026-03-24", "open": 9.32, "high": 9.65, "low": 9.22, "close": 9.64, "volume": 544940, "amount": 0, "pct_change": 5.01}, {"date": "2026-03-25", "open": 9.75, "high": 10.49, "low": 9.6, "close": 10.22, "volume": 872138, "amount": 0, "pct_change": 6.02}, {"date": "2026-03-26", "open": 10.25, "high": 10.65, "low": 9.92, "close": 10.46, "volume": 1001152, "amount": 0, "pct_change": 2.35}, {"date": "2026-03-27", "open": 10.2, "high": 10.34, "low": 9.9, "close": 10.14, "volume": 638674, "amount": 0, "pct_change": -3.06}, {"date": "2026-03-30", "open": 10.11, "high": 10.22, "low": 9.36, "close": 9.47, "volume": 605768, "amount": 0, "pct_change": -6.61}, {"date": "2026-03-31", "open": 9.55, "high": 9.67, "low": 9.17, "close": 9.2, "volume": 459895, "amount": 0, "pct_change": -2.85}, {"date": "2026-04-01", "open": 9.39, "high": 9.48, "low": 9.1, "close": 9.22, "volume": 353204, "amount": 0, "pct_change": 0.22}, {"date": "2026-04-02", "open": 9.2, "high": 9.27, "low": 8.84, "close": 8.94, "volume": 397476, "amount": 0, "pct_change": -3.04}, {"date": "2026-04-03", "open": 8.9, "high": 8.95, "low": 8.67, "close": 8.69, "volume": 260642, "amount": 0, "pct_change": -2.8}]